tubo/__init__.py
tubo/tubo.py
tubo/test/__init__.py
tubo/test/test1.py
tubo/test/test2.py
tubo-0.1.1.dist-info/DESCRIPTION.rst
tubo-0.1.1.dist-info/METADATA
tubo-0.1.1.dist-info/metadata.json
tubo-0.1.1.dist-info/RECORD
tubo-0.1.1.dist-info/top_level.txt
tubo-0.1.1.dist-info/WHEEL
