Metadata-Version: 2.0
Name: tubo
Version: 0.1.1
Summary: A pipeline library for Python that cuts down your boilerplate code.
Home-page: http://github.com/themiurgo/tubo
Author: Antonio Lima
Author-email: anto87@gmail.com
License: MIT
Platform: UNKNOWN
